hfinger/__init__.py
hfinger/__main__.py
hfinger/analysis.py
hfinger/configs.py
hfinger/hfinger_core.py
hfinger/hfinger_exceptions.py
hfinger/hreader.py
hfinger/tshark_wrappers.py
hfinger/uri_reader.py
hfinger/configs/accept.json
hfinger/configs/content-type.json
hfinger/configs/extensions.txt
hfinger/configs/headerslow.json
hfinger-0.2.2.dist-info/LICENSE
hfinger-0.2.2.dist-info/METADATA
hfinger-0.2.2.dist-info/WHEEL
hfinger-0.2.2.dist-info/entry_points.txt
hfinger-0.2.2.dist-info/top_level.txt
hfinger-0.2.2.dist-info/RECORD
