Metadata-Version: 2.1
Name: hfinger
Version: 0.2.2
Summary: Hfinger - fingerprinting malware HTTP requests stored in pcap files
Home-page: https://github.com/CERT-Polska/hfinger
Author: Piotr Białczak
Author-email: piotrb@cert.pl
License: UNKNOWN
Platform: UNKNOWN
Classifier: Development Status :: 3 - Alpha
Classifier: License :: OSI Approved :: GNU General Public License v3 (GPLv3)
Classifier: Programming Language :: Python :: 3
Requires-Python: >=3.3
License-File: LICENSE
Requires-Dist: fnvhash (>=0.1.0)
Requires-Dist: python-magic (>=0.4.18)
